{"GlobalPropertiesHash":"lo5eeWMpD/aP7SpahyuFWFECD5kgyLQXC8MwL7ctcKA=","FingerprintPatternsHash":"gq3WsqcKBUGTSNle7RKKyXRIwh7M8ccEqOqYvIzoM04=","PropertyOverridesHash":"8ZRc1sGeVrPBx4lD717BgRaQekyh78QKV9SKsdt638U=","InputHashes":["KyYJp2EePQgpP\u002BmaOaRLq3V8rVrtODQP1AWr08EKlqY=","pXsQHi9uq2eqTlJ\u002BdaqbE\u002Brs2LTnbkpSLwh47H0Kr0w=","T1pvAG4Q/TUnRxi5pWThQUoZ\u002B6MFURAidtmjjTfQ0rU="],"CachedAssets":{"KyYJp2EePQgpP\u002BmaOaRLq3V8rVrtODQP1AWr08EKlqY=":{"Identity":"C:\\Users\\ZaRZoR\\Desktop\\Valens\\valens\\Back-end\\src\\ValensApi.API\\wwwroot\\.gitkeep","SourceId":"ValensApi.API","SourceType":"Discovered","ContentRoot":"C:\\Users\\ZaRZoR\\Desktop\\Valens\\valens\\Back-end\\src\\ValensApi.API\\wwwroot\\","BasePath":"/","RelativePath":"#[.{fingerprint}]?.gitkeep","AssetKind":"All","AssetMode":"All","AssetRole":"Primary","AssetMergeBehavior":null,"AssetMergeSource":"","RelatedAsset":null,"AssetTraitName":null,"AssetTraitValue":null,"Fingerprint":"kq887z7idc","Integrity":"PKGE4qWcnooYqmdXHQRd1z6opNGUyM7tYJqlBIOFlPA=","CopyToOutputDirectory":"Never","CopyToPublishDirectory":"PreserveNewest","OriginalItemSpec":"wwwroot\\.gitkeep","FileLength":32,"LastWriteTime":"2026-06-27T16:01:15.5153483+00:00"}},"CachedCopyCandidates":{}}